format_docstring/__init__.py
format_docstring/base_fixer.py
format_docstring/config.py
format_docstring/docstring_rewriter.py
format_docstring/line_wrap_google.py
format_docstring/line_wrap_numpy.py
format_docstring/line_wrap_utils.py
format_docstring/main_jupyter.py
format_docstring/main_py.py
format_docstring-0.2.7.dist-info/licenses/LICENSE
format_docstring-0.2.7.dist-info/METADATA
format_docstring-0.2.7.dist-info/WHEEL
format_docstring-0.2.7.dist-info/entry_points.txt
format_docstring-0.2.7.dist-info/top_level.txt
format_docstring-0.2.7.dist-info/RECORD
