Metadata-Version: 2.4
Name: format-docstring
Version: 0.2.7
Summary: A Python formatter to wrap/adjust docstring lines
Author-email: jsh9 <25124332+jsh9@users.noreply.github.com>
Maintainer-email: jsh9 <25124332+jsh9@users.noreply.github.com>
License: MIT
Project-URL: Homepage, https://github.com/your/repo
Project-URL: Issues, https://github.com/your/repo/issues
Project-URL: Repository, https://github.com/your/repo.git
Keywords: code-style,docstring,formatter,python
Classifier: Development Status :: 3 - Alpha
Classifier: Environment :: Console
Classifier: Intended Audience :: Developers
Classifier: License :: OSI Approved :: MIT License
Classifier: Operating System :: OS Independent
Classifier: Programming Language :: Python :: 3 :: Only
Classifier: Programming Language :: Python :: 3
Classifier: Programming Language :: Python :: 3.10
Classifier: Programming Language :: Python :: 3.11
Classifier: Programming Language :: Python :: 3.12
Classifier: Programming Language :: Python
Classifier: Topic :: Software Development :: Libraries :: Python Modules
Classifier: Topic :: Software Development :: Quality Assurance
Requires-Python: >=3.10
License-File: LICENSE
Requires-Dist: click>=8.0
Requires-Dist: jupyter-notebook-parser>=0.1.4
Requires-Dist: tomli>=1.1.0; python_version < "3.11"
Dynamic: license-file
